nat/meta/pypi.md
nat/plugins/semantic_kernel/__init__.py
nat/plugins/semantic_kernel/llm.py
nat/plugins/semantic_kernel/register.py
nat/plugins/semantic_kernel/tool_wrapper.py
nvidia_nat_semantic_kernel-1.3.1.dist-info/licenses/LICENSE-3rd-party.txt
nvidia_nat_semantic_kernel-1.3.1.dist-info/licenses/LICENSE.md
nvidia_nat_semantic_kernel-1.3.1.dist-info/METADATA
nvidia_nat_semantic_kernel-1.3.1.dist-info/WHEEL
nvidia_nat_semantic_kernel-1.3.1.dist-info/entry_points.txt
nvidia_nat_semantic_kernel-1.3.1.dist-info/top_level.txt
nvidia_nat_semantic_kernel-1.3.1.dist-info/RECORD
